mspasspy.cpython-36m-x86_64-linux-gnu.so
mspasspy-0.0.1.dist-info/DESCRIPTION.rst
mspasspy-0.0.1.dist-info/METADATA
mspasspy-0.0.1.dist-info/RECORD
mspasspy-0.0.1.dist-info/WHEEL
mspasspy-0.0.1.dist-info/metadata.json
mspasspy-0.0.1.dist-info/top_level.txt
