Metadata-Version: 2.0
Name: mspasspy
Version: 0.0.1
Summary: Massive Parallel Analysis System for Seismologists
Home-page: UNKNOWN
Author: Ian Wang
Author-email: yinzhi.wang.cug@gmail.com
License: UNKNOWN
Platform: UNKNOWN
